infra_buddy_too/__init__.py
infra_buddy_too/commandline.py
infra_buddy_too/aws/__init__.py
infra_buddy_too/aws/cloudformation.py
infra_buddy_too/aws/cloudwatch_logs.py
infra_buddy_too/aws/config.py
infra_buddy_too/aws/ecs.py
infra_buddy_too/aws/s3.py
infra_buddy_too/commands/__init__.py
infra_buddy_too/commands/bootstrap/__init__.py
infra_buddy_too/commands/bootstrap/command.py
infra_buddy_too/commands/deploy_cloudformation/__init__.py
infra_buddy_too/commands/deploy_cloudformation/command.py
infra_buddy_too/commands/deploy_service/__init__.py
infra_buddy_too/commands/deploy_service/command.py
infra_buddy_too/commands/generate_artifact_manifest/__init__.py
infra_buddy_too/commands/generate_artifact_manifest/command.py
infra_buddy_too/commands/generate_service_definition/__init__.py
infra_buddy_too/commands/generate_service_definition/command.py
infra_buddy_too/commands/introspect/__init__.py
infra_buddy_too/commands/introspect/command.py
infra_buddy_too/commands/validate_template/__init__.py
infra_buddy_too/commands/validate_template/command.py
infra_buddy_too/context/__init__.py
infra_buddy_too/context/artifact_definition.py
infra_buddy_too/context/deploy_ctx.py
infra_buddy_too/context/monitor_definition.py
infra_buddy_too/context/service_definition.py
infra_buddy_too/deploy/__init__.py
infra_buddy_too/deploy/cloudformation_deploy.py
infra_buddy_too/deploy/datadog_monitor_deploy.py
infra_buddy_too/deploy/deploy.py
infra_buddy_too/deploy/ecs_deploy.py
infra_buddy_too/deploy/s3_deploy.py
infra_buddy_too/notifier/__init__.py
infra_buddy_too/notifier/datadog_notifier.py
infra_buddy_too/template/__init__.py
infra_buddy_too/template/builtin-templates.json
infra_buddy_too/template/template.py
infra_buddy_too/template/template_manager.py
infra_buddy_too/utility/__init__.py
infra_buddy_too/utility/exception.py
infra_buddy_too/utility/helper_functions.py
infra_buddy_too/utility/print_utility.py
infra_buddy_too/utility/waitfor.py
infra_buddy_too-75.data/scripts/infra-buddy
infra_buddy_too-75.dist-info/METADATA
infra_buddy_too-75.dist-info/WHEEL
infra_buddy_too-75.dist-info/namespace_packages.txt
infra_buddy_too-75.dist-info/top_level.txt
infra_buddy_too-75.dist-info/zip-safe
infra_buddy_too-75.dist-info/RECORD
