Metadata-Version: 2.4
Name: infra-buddy-too
Version: 75
Summary: CLI for deploying micro-services
Home-page: https://github.com/Nudge-Security/infra-buddy
Author: 
Author-email: 
Maintainer: 
Maintainer-email: 
License: Apache 2.0
Classifier: Development Status :: 3 - Alpha
Classifier: Programming Language :: Python
Requires-Python: >=3.6.0
Requires-Dist: click
Requires-Dist: boto3
Requires-Dist: pydash==6.0.0
Requires-Dist: jsonschema
Requires-Dist: requests
Requires-Dist: datadog
Requires-Dist: botocore
Dynamic: classifier
Dynamic: description
Dynamic: home-page
Dynamic: keywords
Dynamic: license
Dynamic: requires-dist
Dynamic: requires-python
Dynamic: summary
